udo/__init__.py
udo/asgroup.py
udo/cluster.py
udo/config.py
udo/deploy.py
udo/launchconfig.py
udo/main.py
udo/util.py
udo-1.0.0rc1.dist-info/DESCRIPTION.rst
udo-1.0.0rc1.dist-info/entry_points.txt
udo-1.0.0rc1.dist-info/METADATA
udo-1.0.0rc1.dist-info/metadata.json
udo-1.0.0rc1.dist-info/RECORD
udo-1.0.0rc1.dist-info/top_level.txt
udo-1.0.0rc1.dist-info/WHEEL
