Metadata-Version: 2.0
Name: udo
Version: 1.0.0rc1
Summary: Automate AWS Deployments
Home-page: http://github.com/revmischa/udo
Author: Mischa Spiegemock
Author-email: revmischa@cpan.org
License: Anyone But RMS
Keywords: devops aws amazon autoscaling orchestration
Platform: any
Classifier: Programming Language :: Python
Classifier: Topic :: System :: Systems Administration
Requires-Dist: Boto (>=2.36.0)
Requires-Dist: PyYAML
Requires-Dist: parallel-ssh
